Verilog Controlador ATM/probador.v
// Declaración del módulo y parámetros
module probador (CLK,Reset,Tarjeta_recibida,PIN,Digito,Digito_STB,Tipo_trans,Monto,Monto_STB,
               Balance_actualizado,Entregar_dinero,Fondos_insuficientes,PIN_incorrecto,Advertencia,Bloqueo 
               );
    // Declaración de entradas y salidas
    output reg CLK,Reset,Tarjeta_recibida,Digito_STB,Tipo_trans,Monto_STB;
    output reg [3:0] Digito;
    output reg [15:0] PIN;
    output reg [31:0] Monto;
    input Balance_actualizado,Entregar_dinero,Fondos_insuficientes,PIN_incorrecto,Advertencia,Bloqueo;

    initial begin
        //Se inician las variables para la prueba
        CLK = 0;
        Reset = 0;
        Monto = 0;
        Monto_STB = 0;
        Tarjeta_recibida = 0;

        //Se resetea el cajero
        #25 Reset = 1;
        #15 Reset = 0;
        
        //Se introduce la tarjeta
        #10 Tarjeta_recibida = 1;
        
        //Se carga el PIN
        #10 PIN = 16'b1111000000000000;

        //Se teclean los digitos del PIN
        
        //Prueba#1: 
        //primer PIN incorrecto
        #10 Digito = 4'b1000;
        #10 Digito_STB = 1;
        #10 Digito_STB = 0;
        #10 Digito = 4'b0000;
        #10 Digito_STB = 1;
        #10 Digito_STB = 0;
        #10 Digito = 4'b0000;
        #10 Digito_STB = 1;
        #10 Digito_STB = 0;
        #10 Digito = 4'b0000;
        #10 Digito_STB = 1;
        #10 Digito_STB = 0;

        //segundo PIN incorrecto
        #10 Digito = 4'b0100;
        #10 Digito_STB = 1;
        #10 Digito_STB = 0;
        #10 Digito = 4'b0000;
        #10 Digito_STB = 1;
        #10 Digito_STB = 0;
        #10 Digito = 4'b0000;
        #10 Digito_STB = 1;
        #10 Digito_STB = 0;
        #10 Digito = 4'b0000;
        #10 Digito_STB = 1;
        #10 Digito_STB = 0;

        //tercer PIN incorrecto
        #10 Digito = 4'b0010;
        #10 Digito_STB = 1;
        #10 Digito_STB = 0;
        #10 Digito = 4'b0000;
        #10 Digito_STB = 1;
        #10 Digito_STB = 0;
        #10 Digito = 4'b0000;
        #10 Digito_STB = 1;
        #10 Digito_STB = 0;
        #10 Digito = 4'b0000;
        #10 Digito_STB = 1;
        #10 Digito_STB = 0;

        //Se resetea para salir del bloqueo
        #25 Reset = 1;
        #15 Reset = 0;
        
        
        //Prueba#2
        //PIN correcto
        #10 Digito = 4'b1111;
        #10 Digito_STB = 1;
        #10 Digito_STB = 0;
        #10 Digito = 4'b0000;
        #10 Digito_STB = 1;
        #10 Digito_STB = 0;
        #10 Digito = 4'b0000;
        #10 Digito_STB = 1;
        #10 Digito_STB = 0;
        #10 Digito = 4'b0000;
        #10 Digito_STB = 1;
        #10 Digito_STB = 0;

        //Se relecciona hacer un deposito
        #10 Tipo_trans = 0;
        #10 Monto = 32'b111111;//se introduce el monto
        #10 Monto_STB = 1;//Señal para actualizar el monto
        #10 Monto_STB = 0;

        //Se selecciona hacer un retiro, con un monto menor al balance
        #10 Tipo_trans = 1;
        #10 Monto = 32'b011111;
        #10 Monto_STB = 1;
        #10 Monto_STB = 0;

        //Se selecciona hacer un retiro, con un monto mayor al balance
        #10 Tipo_trans = 1;
        #10 Monto = 32'b111111;
        #10 Monto_STB = 1;
        #10 Monto_STB = 0;


        #30 $finish;
    end

    always begin
        #5 CLK = !CLK;
    end
endmodule

Controlador ATM/design.sv
module cajero (CLK,Reset,Tarjeta_recibida,PIN,Digito,Digito_STB,Tipo_trans,Monto,Monto_STB,
               Balance_actualizado,Entregar_dinero,Fondos_insuficientes,PIN_incorrecto,Advertencia,Bloqueo
            );
    input CLK,Reset,Tarjeta_recibida,Digito_STB,Tipo_trans,Monto_STB;
    input [3:0] Digito;
    input [15:0] PIN;
    input [31:0] Monto;

    output reg Balance_actualizado,Entregar_dinero,Fondos_insuficientes,PIN_incorrecto,Advertencia,Bloqueo;


    // Estados
    parameter ESPERA_TARJETA = 3'b000; //valor que representa el estado inicial de la máquina de estados (000).
    parameter VERIFICACION_PIN = 3'b001; //valor que representa el estado en el que se verifica el número PIN ingresado (001).
    parameter SELECCION_TRANSACCION = 3'b010; //valor que representa el estado en el que se selecciona el tipo de transacción a realizar (010).
    parameter DEPOSITO = 3'b011; //valor que representa el estado en el que se realiza una transacción de depósito (011).
    parameter RETIRO = 3'b100; //valor que representa el estado en el que se realiza una transacción de retiro (100).
    parameter BLOQUEADO = 3'b101; //valor que representa el estado en el que la tarjeta ha sido bloqueada (101).


    // Declaración de los registros internos
    reg [63:0] Balance; //registro de 64 bits que representa el balance actual del usuario.
    integer intentos_pin; //registro de enteros que lleva la cuenta de los intentos de PIN incorrectos.


    // Declaración de las señales internas
    reg [15:0] PIN_teclado; //registro de 16 bits que almacena el número PIN ingresado por el usuario en el teclado.


    // Definición de la máquina de estados
    reg [2:0] estado_actual;
    reg [2:0] estado_prox;

    always @ (posedge CLK) begin
            //Con en Reset se envian todos los valores a 0
            if (Reset) begin
                estado_actual        <= ESPERA_TARJETA;
                Balance_actualizado  <= 1'b0;
                Entregar_dinero      <= 1'b0;
                Fondos_insuficientes <= 1'b0;
                PIN_incorrecto       <= 1'b0;
                Advertencia          <= 1'b0;
                Bloqueo              <= 1'b0;
                PIN_teclado          <= 16'b0;
                Balance              <= 64'b0;
                intentos_pin         = 0;
            end
            else begin
                estado_actual <= estado_prox;
                //Registro desplazante para guardar los digetos del PIN
                if (Digito_STB) begin
                    PIN_teclado[3:0] <= Digito;
                    PIN_teclado[7:4] <= PIN_teclado[3:0];
                    PIN_teclado[11:8] <= PIN_teclado[7:4];
                    PIN_teclado[15:12] <= PIN_teclado[11:8];   
                end
            end
    end
               
    //Definir lógica combinacional
    //Case de los estados
    always @ (*) begin
        case (estado_actual)
            //Se inicia esperando la tarjeta, si se recibe esta se pasa a verificar el PIN
            ESPERA_TARJETA: begin
                if (Tarjeta_recibida) begin
                    estado_prox <= VERIFICACION_PIN;
                end
                else estado_prox <= ESPERA_TARJETA;
            end
            VERIFICACION_PIN: begin
                //si el PIN es incorrecto se levanta la señal y se aumenta en 1 el numero de intentos  
                if (PIN_teclado != PIN) begin
                    PIN_incorrecto <= 1'b1;
                    intentos_pin = intentos_pin + 1;
                //Dado que el PIN_teclado se actualiza 4 veces, una con cada vez que se ingresa un digito
                //se tiene que si se introdujo 8 veces mal los digitos del pin se levanta la advertencia
                if (intentos_pin == 8) begin
                    Advertencia <= 1'b1;
                    estado_prox <= VERIFICACION_PIN;
                end
                //se tiene que si se introdujo 12 veces mal los digitos del pin se levanta el bloqueo
                //ademas se va al estado de bloqueado
                if (intentos_pin == 12) begin
                    Bloqueo <= 1'b1;
                    estado_prox <= BLOQUEADO;
                end end
                //Si se introduce bien el pin se pasa al estado se seleccion de transaccion
                if (PIN_teclado == PIN) begin
                    PIN_incorrecto <= 1'b0;
                    estado_prox <= SELECCION_TRANSACCION;
                end 
                //else estado_prox <= VERIFICACION_PIN;
            end

            BLOQUEADO: begin
                // en este estado de bloqueo solo se puede salir utilizando la señal de reset
                if (Reset == 0) begin
                    if (Reset == 1) begin
                        estado_prox <= ESPERA_TARJETA;
                    end
                end
                else estado_prox <= BLOQUEADO;
            end

            SELECCION_TRANSACCION: begin
                //Si Tipo_trans = 0, se va al estado de deposito
                if (Tipo_trans == 0) begin
                    estado_prox <= DEPOSITO;
                end
                //Si Tipo_trans = 1, se va al estado de retiro
                else if (Tipo_trans == 1) begin
                    estado_prox <= RETIRO;
                end
                else estado_prox <= SELECCION_TRANSACCION;
            end

            DEPOSITO: begin
                //Si se tiene la señal de Monto_STB se actualiza el balance
                if (Monto_STB == 1) begin
                    Balance = Balance + Monto;
                    Balance_actualizado <= 1'b1;
                    estado_prox <= SELECCION_TRANSACCION;
                end
                else begin
                    Balance_actualizado = 1'b0;
                    estado_prox <= SELECCION_TRANSACCION;
                end
            end
            RETIRO: begin
                //Si se tiene la señal de Monto_STB y Monto <= Balance  se actualiza el balance y se da el dinero
                if (Monto_STB == 1) begin
                    if (Monto <= Balance) begin
                        Balance = Balance - Monto;
                        Balance_actualizado = 1'b1;
                        Entregar_dinero = 1'b1;
                        estado_prox <= SELECCION_TRANSACCION;
                    end 
                    //Si se tiene la señal de Monto_STB y Monto > Balance se activa Fondos_insuficientes
                    else begin
                        Fondos_insuficientes <= 1'b1;
                        Balance_actualizado = 1'b0;
                        Entregar_dinero = 1'b0;
                        estado_prox <= SELECCION_TRANSACCION;
                    end
                end
                else begin
                    Balance_actualizado = 1'b0;
                    estado_prox <= SELECCION_TRANSACCION;
                end
                
            end
            default: begin
                estado_prox <= ESPERA_TARJETA;
            end
        endcase
    end
endmodule

Verilog Controlador ATM/testbench.sv
`include "probador.v"
//`include "design.sv"
                                        
// Testbench Code Goes here
module me_tb;

    wire CLK,Reset,Tarjeta_recibida,Digito_STB,Tipo_trans,Monto_STB;
    wire [3:0] Digito;
    wire [15:0] PIN;
    wire [31:0] Monto;
    wire Balance_actualizado,Entregar_dinero,Fondos_insuficientes,PIN_incorrecto,Advertencia,Bloqueo;

    initial begin
        $dumpfile("test.vcd");
        $dumpvars(-1, cajero2);
    end

    cajero cajero2 (
        .CLK (CLK),
        .Reset (Reset),
        .Tarjeta_recibida(Tarjeta_recibida),
        .PIN(PIN),
        .Digito(Digito),
        .Digito_STB(Digito_STB),
        .Tipo_trans(Tipo_trans),
        .Monto(Monto),
        .Monto_STB(Monto_STB),
        .Balance_actualizado(Balance_actualizado),
        .Entregar_dinero(Entregar_dinero),
        .Fondos_insuficientes(Fondos_insuficientes),
        .PIN_incorrecto(PIN_incorrecto),
        .Advertencia(Advertencia),
        .Bloqueo(Bloqueo)
    );

    probador PROB_cajero2 (
        .CLK (CLK),
        .Reset (Reset),
        .Tarjeta_recibida(Tarjeta_recibida),
        .PIN(PIN),
        .Digito(Digito),
        .Digito_STB(Digito_STB),
        .Tipo_trans(Tipo_trans),
        .Monto(Monto),
        .Monto_STB(Monto_STB),
        .Balance_actualizado(Balance_actualizado),
        .Entregar_dinero(Entregar_dinero),
        .Fondos_insuficientes(Fondos_insuficientes),
        .PIN_incorrecto(PIN_incorrecto),
        .Advertencia(Advertencia),
        .Bloqueo(Bloqueo)
    );
endmodule

Controlador ATM/test.vcd
$date
	Thu Jul 20 16:58:46 2023
$end
$version
	Icarus Verilog
$end
$timescale
	1s
$end
$scope module me_tb $end
$scope module cajero2 $end
$var wire 1 ! CLK $end
$var wire 4 " Digito [3:0] $end
$var wire 1 # Digito_STB $end
$var wire 32 $ Monto [31:0] $end
$var wire 1 % Monto_STB $end
$var wire 16 & PIN [15:0] $end
$var wire 1 ' Reset $end
$var wire 1 ( Tarjeta_recibida $end
$var wire 1 ) Tipo_trans $end
$var reg 1 * Advertencia $end
$var reg 64 + Balance [63:0] $end
$var reg 1 , Balance_actualizado $end
$var reg 1 - Bloqueo $end
$var reg 1 . Entregar_dinero $end
$var reg 1 / Fondos_insuficientes $end
$var reg 1 0 PIN_incorrecto $end
$var reg 16 1 PIN_teclado [15:0] $end
$var reg 3 2 estado_actual [2:0] $end
$var reg 3 3 estado_prox [2:0] $end
$var integer 32 4 intentos_pin [31:0] $end
$upscope $end
$upscope $end
$enddefinitions $end
#0
$dumpvars
bx 4
b0 3
bx 2
bx 1
x0
x/
x.
x-
x,
bx +
x*
x)
0(
0'
bx &
0%
b0 $
x#
bx "
0!
$end
#5
b0 2
1!
#10
0!
#15
1!
#20
0!
#25
b0 +
b0 1
0-
0*
00
0/
0.
0,
b0 4
1!
1'
#30
0!
#35
1!
#40
0!
0'
#45
1!
#50
b1 3
0!
1(
#55
b1 2
1!
#60
10
b1 4
0!
b1111000000000000 &
#65
1!
#70
0!
b1000 "
#75
1!
#80
0!
1#
#85
b10 4
b1000 1
1!
#90
0!
0#
#95
1!
#100
0!
b0 "
#105
1!
#110
0!
1#
#115
b11 4
b10000000 1
1!
#120
0!
0#
#125
1!
#130
0!
#135
1!
#140
0!
1#
#145
b100 4
b100000000000 1
1!
#150
0!
0#
#155
1!
#160
0!
#165
1!
#170
0!
1#
#175
b101 4
b1000000000000000 1
1!
#180
0!
0#
#185
1!
#190
0!
b100 "
#195
1!
#200
0!
1#
#205
b110 4
b100 1
1!
#210
0!
0#
#215
1!
#220
0!
b0 "
#225
1!
#230
0!
1#
#235
b111 4
b1000000 1
1!
#240
0!
0#
#245
1!
#250
0!
#255
1!
#260
0!
1#
#265
1*
b1000 4
b10000000000 1
1!
#270
0!
0#
#275
1!
#280
0!
#285
1!
#290
0!
1#
#295
b1001 4
b100000000000000 1
1!
#300
0!
0#
#305
1!
#310
0!
b10 "
#315
1!
#320
0!
1#
#325
b1010 4
b10 1
1!
#330
0!
0#
#335
1!
#340
0!
b0 "
#345
1!
#350
0!
1#
#355
b1011 4
b100000 1
1!
#360
0!
0#
#365
1!
#370
0!
#375
1!
#380
0!
1#
#385
b101 3
1-
b1100 4
b1000000000 1
1!
#390
0!
0#
#395
b101 2
1!
#400
0!
#405
1!
#410
0!
1#
#415
b10000000000000 1
1!
#420
0!
0#
#425
1!
#430
0!
#435
1!
#440
0!
#445
b1 3
b0 1
0-
0*
00
b0 2
b0 4
1!
1'
#450
0!
#455
1!
#460
0!
0'
#465
10
b1 4
b1 2
1!
#470
0!
b1111 "
#475
1!
#480
0!
1#
#485
b10 4
b1111 1
1!
#490
0!
0#
#495
1!
#500
0!
b0 "
#505
1!
#510
0!
1#
#515
b11 4
b11110000 1
1!
#520
0!
0#
#525
1!
#530
0!
#535
1!
#540
0!
1#
#545
b100 4
b111100000000 1
1!
#550
0!
0#
#555
1!
#560
0!
#565
1!
#570
0!
1#
#575
b10 3
00
b1111000000000000 1
1!
#580
0!
0#
#585
b10 2
1!
#590
b11 3
0!
0)
#595
b10 3
b11 2
1!
#600
0!
b111111 $
#605
b11 3
b10 2
1!
#610
0!
1%
#615
b10 3
1,
b111111 +
b11 2
1!
#620
0,
0!
0%
#625
b11 3
b10 2
1!
#630
b100 3
0!
1)
#635
b10 3
b100 2
1!
#640
0!
b11111 $
#645
b100 3
b10 2
1!
#650
0!
1%
#655
b10 3
1.
1,
b100000 +
b100 2
1!
#660
0,
0!
0%
#665
b100 3
b10 2
1!
#670
0!
#675
b10 3
b100 2
1!
#680
0!
b111111 $
#685
b100 3
b10 2
1!
#690
0!
1%
#695
b10 3
1/
0.
b100 2
1!
#700
0!
0%
#705
b100 3
b10 2
1!
#710
0!
#715
b10 3
b100 2
1!
#720
0!
#725
b100 3
b10 2
1!
