Verilog Diseño de un generador y un receptor de transacciones I/i2c_receptor.v
`timescale 1ns / 1ps
module i2c_receptor(
    input clk,
    input reset,
    input [6:0] i2c_addr2,//dirreccion del receptor
    input [15:0] rd_data,//salida del generador, data que se debe leer
    input sda_out,//salida de generador
    input scl,//Reloj a 25%
    input sda_oe,// inducacion de quien controla el bus

	output sda_in,//salida sda de receptor a generador
    output reg [15:0] wr_data //salida del receptor, data que se debe escribir
	);
	
	//Se instancian algunos parametros para los estados
	localparam READ_ADDR = 0;//lectura de la dirreccion
	localparam SEND_ACK = 1;//enviar pimer A
	localparam READ_DATA = 2;//lectura
	localparam WRITE_DATA = 3;//escritura
	localparam SEND_ACK2 = 4;//enviar segundo A
	localparam READ_ACK = 5;//leer primer A
	localparam READ_ACK2 = 6;//leer segundo A
	
	reg sda_o = 0;//salida de sda_in
	reg start = 0;//registro para saber si se recibio la condicion de start
	reg byte_counter=0;//contador del byte de datos que se esta enviando o recibiendo
	reg [7:0] addr;// registro de la dirreccion recibida
	reg [7:0] counter;//Contador para la lectura y escritura
	reg [7:0] state = 0;// registro de estado
	reg [7:0] data_in;// Byte que se esta recibiendo
	wire [7:0] rd_data1 = rd_data[7:0];//primer byte que se recibe
    wire [7:0] rd_data2 = rd_data[15:8];//primer byte que se recibe
	reg [15:0] wr_data_master_to_slave;//data que se escribio

	assign sda_in = (sda_oe == 0) ? sda_o : 0;// asigancion de sda_in con sda_o cuando el receptor controla el bus
	

	//analisis de la señal de sda_out para ver si se tiene la condicion de start o stop
	always @( posedge sda_out) begin
		if ((start == 0) && (scl == 1)) begin
			start <= 1;	
			counter <= 7;
		end
	end
	
	always @( negedge sda_out) begin
		if ((start == 1) && (scl == 1)) begin
			state <= READ_ADDR;
			start <= 0;
		end
	end
	
	//logica de estados
	always @(posedge scl, negedge reset) begin
		if(reset == 0) begin//si no hay reset las salidas se ponen en 0
			counter <= 0;
            wr_data <= 0;
            wr_data_master_to_slave <= 0;
			sda_o <= 0;
			data_in <= 0;
		end	
		if (start == 1) begin //si se recibio al condicon de start se pasa a leer o escribir
			case(state)
				//lectura de la dirrecion
				READ_ADDR: begin //se lee la dirrecion enviada
					wr_data = 16'b1100110011001100;//se establece el wr_data
					addr[counter] <= sda_out;//se guardan los bits de la dirreccion y el rnw
					if(counter == 0) state <= SEND_ACK;//se envia A 
					else counter <= counter - 1;//se disminuye el contador que recorre la dirreccion a recibida			
				end
				
				//comprbacion de la dirreccion
				SEND_ACK: begin
					if(addr[7:1] == i2c_addr2) begin//si la dirrecion es correcta se lee el rnw adjunto
						counter <= 7;//se reinicia el contador de data a enviar o recibir
						if(addr[0] == 0) begin 
							state <= READ_DATA;//si rnw=o se quiere leer
						end
						else state <= WRITE_DATA;// si rnw=1 se quiere escribir
					end
				end
				
				//estado de lectura
				READ_DATA: begin
					data_in[counter] <= sda_out;//se agrega a data_in el byte que se esta leyendo
					//cuando se lee el primer byte se pasa al segundo
					if (byte_counter == 0 && counter == 0) begin//se escibe el A de que se leyo el primer byte
                        state <= SEND_ACK;//se escibe el A de que se leyo el primer byte
                        byte_counter <= 1;
                    end
                    else if(byte_counter == 1 &&counter == 0) begin//Se agrega el sgundo byte leido
						wr_data_master_to_slave[7:0] <= data_in;
						state <= SEND_ACK2;//se escribe el A de que se leyo el segundo byte
						byte_counter <= 0;
					end
					else counter <= counter - 1;//se disminuye el contador que recorre el byte a leer
				end
				
				//estado de escritura del primer A
				SEND_ACK2: begin
					state <= READ_ADDR;					
				end
				
				//estado de escritura
				WRITE_DATA: begin
					//Se envia el primer byte y se compuebra el A
					if (byte_counter == 0 && counter == 0) begin
                        state <= READ_ACK;
                        byte_counter <= 1;
                    end
					//Se envia el segundo byte y comprueba el segundo A
                    if(byte_counter == 1 && counter == 0) begin
						state <= READ_ACK2;
					end 
					if(counter!=0) counter <= counter - 1;//se disminuye el contador que recorre el byte a escribir
				end

				//estado de lectura de A
				READ_ACK: begin//se lee el A, si este correcto se verifica si se quiere leer o escribir
					counter <= 7;//Se inicia el contador
					if ((sda_out == 0)) state <= WRITE_DATA;
					else state <= READ_ADDR;
				end

				//estado de lectura del segundo A
				READ_ACK2: begin
					if ((sda_out == 1)) state <= READ_ADDR;
					else state <= READ_ADDR;
				end
				
			endcase
		end
	end
	
	always @(negedge scl) begin
		case(state)
			//estado de escritura del primer A
			SEND_ACK: begin
				sda_o <= 0;	//se escribe el A
			end
			
			//estado de lectura
			READ_DATA: begin
				sda_o <= 0;
				wr_data_master_to_slave[15:8] <= data_in;//se guarda el primer byte leido
			end
			
			//estado de escritura
			WRITE_DATA: begin
				if (byte_counter == 0) sda_o <= rd_data1[counter];// se envia por sda_in el primer byte
                else sda_o <= rd_data2[counter];// se envia por sda_in el segundo byte
			end
			
			//estado de escritura del segundo A
			SEND_ACK2: begin
				sda_o <= 0;//se escribe el A
			end
		endcase
	end
endmodule

Diseño de un generador y un receptor de transacciones I/i2c_generador.v
`timescale 1ns / 1ps
module i2c_generador(
	//Se definen los inputs y auputs segun el enunciado
	input wire clk,
	input wire reset,
	input wire start_stb,
	input wire rnw, // inducacion de si se va a leer o escribir
	input wire [6:0] i2c_addr1, //dirreccion del receptor al que se quiere enviar
	input sda_in, //sda de receptor a generador
	input wire [15:0] wr_data, //salida del receptor, data que se debe escribir

	output wire scl,//Reloj a 25%
	output sda_out,//salida de generador
	output reg sda_oe,// inducacion de quien controla el bus
	output reg [15:0] rd_data //salida del generador, data que se debe leer
	);

	//Se instancian algunos parametros para los estados
	localparam IDLE = 0;//estado de reposo
	localparam START = 1;//estado de inicio
	localparam ADDRESS = 2;//estado de envio de la direccion
	localparam READ_ACK = 3;//estado de lectura de A
	localparam WRITE_DATA = 4;//estado de escritura
	localparam WRITE_ACK = 5;//estado de escritura de A
	localparam READ_DATA = 6;//estado de lectura
	localparam READ_ACK2 = 7;//estado de lectura del segundo A
    localparam WRITE_ACK2 = 8;//estado de escritura del se segundo A
	localparam STOP = 9;// estado de parada

	localparam DIVIDE_BY = 4;//varibale para la division del clk

	reg byte_counter=0;//contador del byte de datos que se esta enviando o recibiendo
	reg sda_o;//salida de sda
	reg scl_enable = 0;// habilitador de scl
	reg i2c_clk = 1;// reloj a 25%
	reg [7:0] state;// registro de estado
	reg [7:0] saved_i2c_addr;// registro de la dirreccion y rnw
	reg [7:0] counter;//Contador para la lectura y escritura
	reg [7:0] counter2 = 0;//contador para realizar scl a 25%
	reg [7:0] data_in;// Byte que se esta recibiendo
    wire [7:0] wr_data1 = wr_data[7:0];//primer byte que se envia 
    wire [7:0] wr_data2 = wr_data[15:8];// segundo byte que se envia
    reg [15:0] rd_data_slave_to_master;//data que se leyo
  
	assign scl = (scl_enable == 0 ) ? 1 : i2c_clk;//asigancion del scl cuando le corresponde encenderse
	assign sda_out = (sda_oe == 1) ? sda_o : 0;// asigancion de sda_out con sda_o cuando el generador controla el bus
	
	//se divide el reloj principal entre 4
	always @(posedge clk) begin
		if (counter2 == (DIVIDE_BY/2) - 1) begin
			i2c_clk <= ~i2c_clk;
			counter2 <= 0;
		end
		else counter2 <= counter2 + 1;
	end 
	
	//se analiza cuando se debe habilitar scl
	always @(negedge i2c_clk, negedge reset) begin
		if(reset == 0) begin
			scl_enable <= 0;
		end 
		else begin
			if ((state == IDLE) || (state == START) || (state == STOP)) begin
				scl_enable <= 0;
			end else begin
				scl_enable <= 1;
			end
		end
	end

	//logica de estados
	always @(posedge i2c_clk, negedge reset) begin
		//si no hay reset las salidas se ponen en 0
		if(reset == 0) begin
			state <= IDLE;
			counter <= 0;
			counter2 <= 0;
            rd_data <= 0;
            rd_data_slave_to_master <= 0;
            sda_o <= 0;
            sda_oe <= 0;
            data_in <= 0;
		end		
		else begin
			case(state)
				//estado de reposo
				IDLE: begin
                    rd_data = 16'b1010101010101010;//se establece el rd_data a leer en caso de entrar en el estado de lectura
					if (start_stb) begin//si se tiene la señal de inicio se pasa al estado de start
                        sda_o <= 1;//se levanta sda_o para indicar la condicion de inicio
						saved_i2c_addr <= {i2c_addr1, rnw};//se une la dirreccion y el rnw
                        state <= START;// se pasa al estado de start
					end
					else state <= IDLE;//si no se recibe la señal de inicio de continua en reposo
				end

				//estado de start
				START: begin
					counter <= 7;//Se inicia el contador
                    state <= ADDRESS;//se pasa al estado de enviar la dirreccion y el rnw
				end

				//estado de envio de dirreccion y rnw
				ADDRESS: begin
					if (counter == 0) begin //si ya se envio todo la dirreccion y el rnw se pasa a comprobar el A
						state <= READ_ACK;
					end 
					else counter <= counter - 1;//se disminuye el contador que recorre la dirreccion a enviar
				end

				//estado de lectura de A
				READ_ACK: begin //se lee el A, si este correcto se verifica si se quiere leer o escribir
					if ((sda_in == 0) ) begin
						counter <= 7;//se reinicia el contador de data a enviar o recibir
						if(saved_i2c_addr[0] == 0) state <= WRITE_DATA;// si rnw=0 se quiere escribir
						else state <= READ_DATA;//si rnw=1 se quiere leer
					end else state <= STOP;// si A es 1 no se recibio correctamente la dirreccion, se para la transmision
				end

				//estado de escritura
				WRITE_DATA: begin
					//Se envia el primer byte y se compuebra el A
                    if (byte_counter == 0 && counter == 0) begin
                        state <= READ_ACK;
                        byte_counter <= 1;
                    end
					
					//Se envia el segundo byte y comprueba el segundo A
                    if(byte_counter == 1 &&counter == 0) begin
						state <= READ_ACK2;
                        byte_counter <= 0;
					end 
					else counter <= counter - 1;//se disminuye el contador que recorre el byte a escribir
				end

				//estado de lectura del segundo A
				READ_ACK2: begin //si se recibe correcto el A se pasa stop
					if ((sda_in == 0) && (start_stb == 1)) state <= IDLE;
					else state <= STOP;
				end

				//estado de lectura
				READ_DATA: begin
					data_in[counter] <= sda_in;//se agrega a data_in el byte que se esta leyendo
					//cuando se lee el primer byte se pasa al segundo
                    if (byte_counter == 0 && counter == 0) begin
                        state <= WRITE_ACK;//se escibe el A de que se leyo el primer byte
                        byte_counter <= 1;
                    end
                    if(byte_counter == 1 &&counter == 0) begin
                        rd_data_slave_to_master[7:0] = data_in;//Se agrega el sgundo byte leido
						state <= WRITE_ACK2;//se escribe el A de que se leyo el segundo byte
                        byte_counter <= 0;
					end 
					else counter <= counter - 1;//se disminuye el contador que recorre el byte a leer
				end
				
				//estado de escritura del primer A
				WRITE_ACK: begin
                    counter <= 7;
					state <= READ_DATA;
				end

				//estado de escritura del segundo A y paso el estado de stop
                WRITE_ACK2: begin
					if ((sda_o == 0) && (start_stb == 1)) state <= IDLE;
					else state <= STOP;
				end

				//estado de stop
				STOP: begin
					state <= IDLE;
				end
			endcase
		end
	end
	
	//acciones adicionales a realizar en cada estado
	always @(negedge i2c_clk, negedge reset) begin
		if(reset == 0) begin
			sda_oe <= 0;
			sda_o <= 0;
		end 
        else begin
			case(state)
				//estado de start
				START: begin
					sda_oe <= 1;
				end
				
				//estado de envio de dirreccion y rnw
				ADDRESS: begin
					sda_o <= saved_i2c_addr[counter];//Se envian un bit a la vez la dirrecion
				end
				
				//estado de lectura de A
				READ_ACK: begin
					sda_oe <= 0;//se le da el control de bus al receptor
                    sda_o <= 0;//se pone sda_out en bajo
				end
				
				//estado de escritura
				WRITE_DATA: begin 
					sda_oe <= 1;//el generador tiene el control del bus
                    if (byte_counter == 0) sda_o <= wr_data1[counter];// se envia por sda_out el primer byte
                    else sda_o <= wr_data2[counter];// se envia por sda_out el segundo byte
				end
				
				//estado de escritura del primer A
				WRITE_ACK: begin
					sda_oe <= 1;
					sda_o <= 0;//se escribe el A
				end

				//estado de escritura del segundo A y paso el estado de stop
                WRITE_ACK2: begin
					sda_oe <= 1;
					sda_o <= 0;//se escribe el A
				end
				
				//estado de lectura
				READ_DATA: begin
					sda_oe <= 0;//se le da el control de bus al receptor
                    sda_o <= 0;
                    rd_data_slave_to_master[15:8] = data_in;//se guarda el primer byte leido		
				end
				
				//estado de lectura del segundo A
                READ_ACK2: begin
					sda_oe <= 0;//se le da el control de bus al receptor
                    sda_o <= 1;
				end

				//estado de stop
				STOP: begin
					sda_oe <= 1;//el generador tiene el control del bus
					sda_o <= 1;//Se crea la condicion de parada
				end
			endcase
		end
	end
endmodule

Diseño de un generador y un receptor de transacciones I/i2c_tester.v
`include "i2c_generador.v"
`include "i2c_receptor.v"
`timescale 1ns / 1ps

module i2c_probador(clk,reset,i2c_addr1,i2c_addr2,start_stb,rnw, rd_data,wr_data,sda_in,sda_out,sda_oe,scl);

	// Inputs
	output reg clk;
	output reg reset=1;
	output reg [6:0] i2c_addr1;//dirreccion a la que se quiere enviar
	output reg [6:0] i2c_addr2;//dirreccion del receptor
	
	output reg start_stb=0;//señal del cpu de inicio
	output reg rnw;//indicador de escritura o lectura

	// Outputs
	output wire [15:0] rd_data;//data a leer
    output wire [15:0] wr_data;//data a escribir

	output wire sda_in;//entrada del generador de lo que se lee
    output wire sda_out;//salida del generador de lo que se escribe
    output wire sda_oe;//inducador de control del bus
	output wire scl;//reloj a 25%

	// Crear una instancia de la unidad bajo prueba (UUT)
	i2c_generador master (
		.clk(clk), 
		.reset(reset), 
		.i2c_addr1(i2c_addr1), 
		.wr_data(wr_data), 
		.start_stb(start_stb), 
		.rnw(rnw), 
		.rd_data(rd_data), 
		.sda_in(sda_in),
        .sda_out(sda_out),
        .sda_oe(sda_oe),  
		.scl(scl)
	);
		
	i2c_receptor slave (
        .clk(clk), 
		.reset(reset), 
		.i2c_addr2(i2c_addr2),
        .rd_data(rd_data), 
        .wr_data(wr_data),
        .sda_in(sda_in),
        .sda_out(sda_out), 
        .sda_oe(sda_oe),  
        .scl(scl)
    );
	
	//reloj principal
	initial begin
		clk = 0;
		forever begin
			clk = #1 ~clk;
		end		
	end

	initial begin
		clk = 0;//se incia el reloj

	//////////prueba1//////////
	//prueba de esritura
		reset = 0;
		// Espere 100 ns para que finalice el restablecimiento
		#100;
		reset = 1;	

		i2c_addr1 = 7'b0111111;//dirreccion a la que se quiere escribir (carne B88263), dirreccion 63=0111111
		i2c_addr2 = 7'b0111111;//dirrecion del receptor
		rnw = 0;//indicacion de que se quiere escribir
		start_stb = 1;//strobe de inicio
		#10;
		start_stb = 0;	
		#250//se da un tiempo para que se complete la transaccion

	//////////prueba2//////////
	//prueba de lectura
        reset = 0;
		#100;// Espere 100 ns para que finalice el restablecimiento
		reset = 1;		
		i2c_addr1 = 7'b0111111;//dirreccion a la que se quiere leer (carne B88263), dirreccion 63=0111111
		i2c_addr2 = 7'b0111111;//dirrecion del receptor
		rnw = 1;//indicacion de que se quiere leer
		start_stb = 1;//strobe de inicio
		#10;
		start_stb = 0;	
		#250//se da un tiempo para que se complete la transaccion

	//////////prueba3//////////
	//prueba de dirrecion distinta
		reset = 0;
		#100;// Espere 100 ns para que finalice el restablecimiento
		reset = 1;		
		i2c_addr1 = 7'b0111111;//dirreccion a la que se quiere escribir (carne B88263), dirreccion 63=0111111
		i2c_addr2 = 7'b0101111;//dirrecion del receptor (distinta a la que se quiere leer)
		rnw = 1;//indicacion de que se quiere leer
		start_stb = 1;//strobe de inicio
		#10;
		start_stb = 0;	
		#250//se da un tiempo para que se complete la transaccion
		$finish;
		
	end      
endmodule

Verilog Diseño de un generador y un receptor de transacciones I/testbench.sv
`include "i2c_tester.v"
`timescale 1ns / 1ps

module i2c_tb;

	// Inputs
	wire clk;
	wire reset;
	wire [6:0] i2c_addr1;
	wire [6:0] i2c_addr2;
	wire [15:0] wr_data;
	wire start_stb;
	wire rnw;

	// Outputs
	wire [15:0] rd_data;

	wire sda_in;
    wire sda_out;
    wire sda_oe;
	wire scl;

	//archivo para guardar la prueba
    initial begin
	    $dumpfile("test.vcd");
        $dumpvars(-1,probador);
    end

	// Crear una instancia de la unidad bajo prueba (UUT)
	i2c_probador probador(
		.clk(clk),
		.reset(reset),
		.i2c_addr1(i2c_addr1),
		.i2c_addr2(i2c_addr2),
		.wr_data(wr_data),
		.start_stb(start_stb),
		.rnw(rnw),

		// Outputs
		.rd_data(rd_data),

		.sda_in(sda_in),
		.sda_out(sda_out),
		.sda_oe(sda_oe),
		.scl(scl)

	);   
endmodule

Verilog Diseño de un generador y un receptor de transacciones I/test.vcd
$date
	Thu Jul 20 16:59:51 2023
$end
$version
	Icarus Verilog
$end
$timescale
	1ps
$end
$scope module i2c_tb $end
$scope module probador $end
$var wire 16 ! rd_data [15:0] $end
$var wire 1 " scl $end
$var wire 1 # sda_in $end
$var wire 1 $ sda_oe $end
$var wire 1 % sda_out $end
$var wire 16 & wr_data [15:0] $end
$var reg 1 ' clk $end
$var reg 7 ( i2c_addr1 [6:0] $end
$var reg 7 ) i2c_addr2 [6:0] $end
$var reg 1 * reset $end
$var reg 1 + rnw $end
$var reg 1 , start_stb $end
$scope module master $end
$var wire 1 - clk $end
$var wire 7 . i2c_addr1 [6:0] $end
$var wire 1 / reset $end
$var wire 1 0 rnw $end
$var wire 1 " scl $end
$var wire 1 # sda_in $end
$var wire 1 % sda_out $end
$var wire 1 1 start_stb $end
$var wire 16 2 wr_data [15:0] $end
$var wire 8 3 wr_data1 [7:0] $end
$var wire 8 4 wr_data2 [7:0] $end
$var reg 1 5 byte_counter $end
$var reg 8 6 counter [7:0] $end
$var reg 8 7 counter2 [7:0] $end
$var reg 8 8 data_in [7:0] $end
$var reg 1 9 i2c_clk $end
$var reg 16 : rd_data [15:0] $end
$var reg 16 ; rd_data_slave_to_master [15:0] $end
$var reg 8 < saved_i2c_addr [7:0] $end
$var reg 1 = scl_enable $end
$var reg 1 > sda_o $end
$var reg 1 ? sda_oe $end
$var reg 8 @ state [7:0] $end
$upscope $end
$scope module slave $end
$var wire 1 - clk $end
$var wire 7 A i2c_addr2 [6:0] $end
$var wire 16 B rd_data [15:0] $end
$var wire 8 C rd_data1 [7:0] $end
$var wire 8 D rd_data2 [7:0] $end
$var wire 1 / reset $end
$var wire 1 " scl $end
$var wire 1 # sda_in $end
$var wire 1 $ sda_oe $end
$var wire 1 % sda_out $end
$var reg 8 E addr [7:0] $end
$var reg 1 F byte_counter $end
$var reg 8 G counter [7:0] $end
$var reg 8 H data_in [7:0] $end
$var reg 1 I sda_o $end
$var reg 1 J start $end
$var reg 8 K state [7:0] $end
$var reg 16 L wr_data [15:0] $end
$var reg 16 M wr_data_master_to_slave [15:0] $end
$upscope $end
$upscope $end
$upscope $end
$enddefinitions $end
#0
$dumpvars
b0 M
b0 L
b0 K
0J
0I
b0 H
b0 G
0F
bx E
b0 D
b0 C
b0 B
bx A
b0 @
0?
0>
0=
bx <
b0 ;
b0 :
19
b0 8
b0 7
b0 6
05
b0 4
b0 3
b0 2
01
x0
0/
bx .
0-
0,
x+
0*
bx )
bx (
0'
b0 &
0%
0$
0#
1"
b0 !
$end
#1000
b1 7
1'
1-
#2000
0'
0-
#3000
b0 7
09
1'
1-
#4000
0'
0-
#5000
b1 7
1'
1-
#6000
0'
0-
#7000
b0 7
19
1'
1-
#8000
0'
0-
#9000
b1 7
1'
1-
#10000
0'
0-
#11000
b0 7
09
1'
1-
#12000
0'
0-
#13000
b1 7
1'
1-
#14000
0'
0-
#15000
b0 7
19
1'
1-
#16000
0'
0-
#17000
b1 7
1'
1-
#18000
0'
0-
#19000
b0 7
09
1'
1-
#20000
0'
0-
#21000
b1 7
1'
1-
#22000
0'
0-
#23000
b0 7
19
1'
1-
#24000
0'
0-
#25000
b1 7
1'
1-
#26000
0'
0-
#27000
b0 7
09
1'
1-
#28000
0'
0-
#29000
b1 7
1'
1-
#30000
0'
0-
#31000
b0 7
19
1'
1-
#32000
0'
0-
#33000
b1 7
1'
1-
#34000
0'
0-
#35000
b0 7
09
1'
1-
#36000
0'
0-
#37000
b1 7
1'
1-
#38000
0'
0-
#39000
b0 7
19
1'
1-
#40000
0'
0-
#41000
b1 7
1'
1-
#42000
0'
0-
#43000
b0 7
09
1'
1-
#44000
0'
0-
#45000
b1 7
1'
1-
#46000
0'
0-
#47000
b0 7
19
1'
1-
#48000
0'
0-
#49000
b1 7
1'
1-
#50000
0'
0-
#51000
b0 7
09
1'
1-
#52000
0'
0-
#53000
b1 7
1'
1-
#54000
0'
0-
#55000
b0 7
19
1'
1-
#56000
0'
0-
#57000
b1 7
1'
1-
#58000
0'
0-
#59000
b0 7
09
1'
1-
#60000
0'
0-
#61000
b1 7
1'
1-
#62000
0'
0-
#63000
b0 7
19
1'
1-
#64000
0'
0-
#65000
b1 7
1'
1-
#66000
0'
0-
#67000
b0 7
09
1'
1-
#68000
0'
0-
#69000
b1 7
1'
1-
#70000
0'
0-
#71000
b0 7
19
1'
1-
#72000
0'
0-
#73000
b1 7
1'
1-
#74000
0'
0-
#75000
b0 7
09
1'
1-
#76000
0'
0-
#77000
b1 7
1'
1-
#78000
0'
0-
#79000
b0 7
19
1'
1-
#80000
0'
0-
#81000
b1 7
1'
1-
#82000
0'
0-
#83000
b0 7
09
1'
1-
#84000
0'
0-
#85000
b1 7
1'
1-
#86000
0'
0-
#87000
b0 7
19
1'
1-
#88000
0'
0-
#89000
b1 7
1'
1-
#90000
0'
0-
#91000
b0 7
09
1'
1-
#92000
0'
0-
#93000
b1 7
1'
1-
#94000
0'
0-
#95000
b0 7
19
1'
1-
#96000
0'
0-
#97000
b1 7
1'
1-
#98000
0'
0-
#99000
b0 7
09
1'
1-
#100000
0'
0-
1,
11
0+
00
b111111 )
b111111 A
b111111 (
b111111 .
1*
1/
#101000
b1 7
1'
1-
#102000
0'
0-
#103000
b1 @
b1111110 <
1>
b10101010 C
b10101010 D
b1010101010101010 :
b1010101010101010 !
b1010101010101010 B
b0 7
19
1'
1-
#104000
0'
0-
#105000
b1 7
1'
1-
#106000
0'
0-
#107000
b111 G
1J
1%
1?
1$
b0 7
09
1'
1-
#108000
0'
0-
#109000
b1 7
1'
1-
#110000
0'
0-
0,
01
#111000
b10 @
b111 6
b0 7
19
1'
1-
#112000
0'
0-
#113000
b1 7
1'
1-
#114000
0'
0-
#115000
0%
0"
0>
1=
b0 7
09
1'
1-
#116000
0'
0-
#117000
b1 7
1'
1-
#118000
0'
0-
#119000
b110 G
b0xxxxxxx E
b110 6
b11001100 4
b11001100 3
b1100110011001100 L
b1100110011001100 &
b1100110011001100 2
1"
b0 7
19
1'
1-
#120000
0'
0-
#121000
b1 7
1'
1-
#122000
0'
0-
#123000
1%
1>
0"
b0 7
09
1'
1-
#124000
0'
0-
#125000
b1 7
1'
1-
#126000
0'
0-
#127000
b101 G
b1xxxxxx E
b101 6
1"
b0 7
19
1'
1-
#128000
0'
0-
#129000
b1 7
1'
1-
#130000
0'
0-
#131000
0"
b0 7
09
1'
1-
#132000
0'
0-
#133000
b1 7
1'
1-
#134000
0'
0-
#135000
b100 G
b11xxxxx E
b100 6
1"
b0 7
19
1'
1-
#136000
0'
0-
#137000
b1 7
1'
1-
#138000
0'
0-
#139000
0"
b0 7
09
1'
1-
#140000
0'
0-
#141000
b1 7
1'
1-
#142000
0'
0-
#143000
b11 G
b111xxxx E
b11 6
1"
b0 7
19
1'
1-
#144000
0'
0-
#145000
b1 7
1'
1-
#146000
0'
0-
#147000
0"
b0 7
09
1'
1-
#148000
0'
0-
#149000
b1 7
1'
1-
#150000
0'
0-
#151000
b10 G
b1111xxx E
b10 6
1"
b0 7
19
1'
1-
#152000
0'
0-
#153000
b1 7
1'
1-
#154000
0'
0-
#155000
0"
b0 7
09
1'
1-
#156000
0'
0-
#157000
b1 7
1'
1-
#158000
0'
0-
#159000
b1 G
b11111xx E
b1 6
1"
b0 7
19
1'
1-
#160000
0'
0-
#161000
b1 7
1'
1-
#162000
0'
0-
#163000
0"
b0 7
09
1'
1-
#164000
0'
0-
#165000
b1 7
1'
1-
#166000
0'
0-
#167000
b0 G
b111111x E
b0 6
1"
b0 7
19
1'
1-
#168000
0'
0-
#169000
b1 7
1'
1-
#170000
0'
0-
#171000
0%
0>
0"
b0 7
09
1'
1-
#172000
0'
0-
#173000
b1 7
1'
1-
#174000
0'
0-
#175000
b1 K
b1111110 E
b11 @
1"
b0 7
19
1'
1-
#176000
0'
0-
#177000
b1 7
1'
1-
#178000
0'
0-
#179000
0?
0$
0"
b0 7
09
1'
1-
#180000
0'
0-
#181000
b1 7
1'
1-
#182000
0'
0-
#183000
b10 K
b111 G
b100 @
b111 6
1"
b0 7
19
1'
1-
#184000
0'
0-
#185000
b1 7
1'
1-
#186000
0'
0-
#187000
1%
b0 M
1>
1?
1$
0"
b0 7
09
1'
1-
#188000
0'
0-
#189000
b1 7
1'
1-
#190000
0'
0-
#191000
b110 G
b10000000 H
b110 6
1"
b0 7
19
1'
1-
#192000
0'
0-
#193000
b1 7
1'
1-
#194000
0'
0-
#195000
b1000000000000000 M
0"
b0 7
09
1'
1-
#196000
0'
0-
#197000
b1 7
1'
1-
#198000
0'
0-
#199000
b101 G
b11000000 H
b101 6
1"
b0 7
19
1'
1-
#200000
0'
0-
#201000
b1 7
1'
1-
#202000
0'
0-
#203000
0%
b1100000000000000 M
0>
0"
b0 7
09
1'
1-
#204000
0'
0-
#205000
b1 7
1'
1-
#206000
0'
0-
#207000
b100 G
b11000000 H
b100 6
1"
b0 7
19
1'
1-
#208000
0'
0-
#209000
b1 7
1'
1-
#210000
0'
0-
#211000
b1100000000000000 M
0"
b0 7
09
1'
1-
#212000
0'
0-
#213000
b1 7
1'
1-
#214000
0'
0-
#215000
b11 G
b11000000 H
b11 6
1"
b0 7
19
1'
1-
#216000
0'
0-
#217000
b1 7
1'
1-
#218000
0'
0-
#219000
1%
b1100000000000000 M
1>
0"
b0 7
09
1'
1-
#220000
0'
0-
#221000
b1 7
1'
1-
#222000
0'
0-
#223000
b10 G
b11001000 H
b10 6
1"
b0 7
19
1'
1-
#224000
0'
0-
#225000
b1 7
1'
1-
#226000
0'
0-
#227000
b1100100000000000 M
0"
b0 7
09
1'
1-
#228000
0'
0-
#229000
b1 7
1'
1-
#230000
0'
0-
#231000
b1 G
b11001100 H
b1 6
1"
b0 7
19
1'
1-
#232000
0'
0-
#233000
b1 7
1'
1-
#234000
0'
0-
#235000
0%
b1100110000000000 M
0>
0"
b0 7
09
1'
1-
#236000
0'
0-
#237000
b1 7
1'
1-
#238000
0'
0-
#239000
b0 G
b11001100 H
b0 6
1"
b0 7
19
1'
1-
#240000
0'
0-
#241000
b1 7
1'
1-
#242000
0'
0-
#243000
b1100110000000000 M
0"
b0 7
09
1'
1-
#244000
0'
0-
#245000
b1 7
1'
1-
#246000
0'
0-
#247000
1F
b1 K
b11001100 H
b11111111 6
15
b11 @
1"
b0 7
19
1'
1-
#248000
0'
0-
#249000
b1 7
1'
1-
#250000
0'
0-
#251000
0?
0$
0"
b0 7
09
1'
1-
#252000
0'
0-
#253000
b1 7
1'
1-
#254000
0'
0-
#255000
b10 K
b111 G
b100 @
b111 6
1"
b0 7
19
1'
1-
#256000
0'
0-
#257000
b1 7
1'
1-
#258000
0'
0-
#259000
1%
b1100110000000000 M
1>
1?
1$
0"
b0 7
09
1'
1-
#260000
0'
0-
#261000
b1 7
1'
1-
#262000
0'
0-
#263000
b110 G
b11001100 H
b110 6
1"
b0 7
19
1'
1-
#264000
0'
0-
#265000
b1 7
1'
1-
#266000
0'
0-
#267000
b1100110000000000 M
0"
b0 7
09
1'
1-
#268000
0'
0-
#269000
b1 7
1'
1-
#270000
0'
0-
#271000
b101 G
b11001100 H
b101 6
1"
b0 7
19
1'
1-
#272000
0'
0-
#273000
b1 7
1'
1-
#274000
0'
0-
#275000
0%
b1100110000000000 M
0>
0"
b0 7
09
1'
1-
#276000
0'
0-
#277000
b1 7
1'
1-
#278000
0'
0-
#279000
b100 G
b11001100 H
b100 6
1"
b0 7
19
1'
1-
#280000
0'
0-
#281000
b1 7
1'
1-
#282000
0'
0-
#283000
b1100110000000000 M
0"
b0 7
09
1'
1-
#284000
0'
0-
#285000
b1 7
1'
1-
#286000
0'
0-
#287000
b11 G
b11001100 H
b11 6
1"
b0 7
19
1'
1-
#288000
0'
0-
#289000
b1 7
1'
1-
#290000
0'
0-
#291000
1%
b1100110000000000 M
1>
0"
b0 7
09
1'
1-
#292000
0'
0-
#293000
b1 7
1'
1-
#294000
0'
0-
#295000
b10 G
b11001100 H
b10 6
1"
b0 7
19
1'
1-
#296000
0'
0-
#297000
b1 7
1'
1-
#298000
0'
0-
#299000
b1100110000000000 M
0"
b0 7
09
1'
1-
#300000
0'
0-
#301000
b1 7
1'
1-
#302000
0'
0-
#303000
b1 G
b11001100 H
b1 6
1"
b0 7
19
1'
1-
#304000
0'
0-
#305000
b1 7
1'
1-
#306000
0'
0-
#307000
0%
b1100110000000000 M
0>
0"
b0 7
09
1'
1-
#308000
0'
0-
#309000
b1 7
1'
1-
#310000
0'
0-
#311000
b0 G
b11001100 H
b0 6
1"
b0 7
19
1'
1-
#312000
0'
0-
#313000
b1 7
1'
1-
#314000
0'
0-
#315000
b1100110000000000 M
0"
b0 7
09
1'
1-
#316000
0'
0-
#317000
b1 7
1'
1-
#318000
0'
0-
#319000
0F
b100 K
b1100110011001100 M
b11001100 H
05
b111 @
1"
b0 7
19
1'
1-
#320000
0'
0-
#321000
b1 7
1'
1-
#322000
0'
0-
#323000
1>
0?
0$
0"
b0 7
09
1'
1-
#324000
0'
0-
#325000
b1 7
1'
1-
#326000
0'
0-
#327000
b0 K
b1001 @
1"
b0 7
19
1'
1-
#328000
0'
0-
#329000
b1 7
1'
1-
#330000
0'
0-
#331000
b1 K
b1111111 E
1%
0=
1?
1$
1"
b0 7
09
1'
1-
#332000
0'
0-
#333000
b1 7
1'
1-
#334000
0'
0-
#335000
b0 @
b0 7
19
1'
1-
#336000
0'
0-
#337000
b1 7
1'
1-
#338000
0'
0-
#339000
b0 7
09
1'
1-
#340000
0'
0-
#341000
b1 7
1'
1-
#342000
0'
0-
#343000
b0 7
19
1'
1-
#344000
0'
0-
